{"mode":"CHARGE_CHANCE","result":"o","chance_info":{"emtpy":"0","ssn":"j2cCTrNkpGjENK1","reg_date":"2022-12-24 23:06:15","uname":"\uc6d0*\ud0dc","pno":null,"profile_image":"","member_type":"0","total_chance":"1010","use_chance":"0","login_today":"10","gift_today":"0","sns_today":"0","add_today":"1000","use_today":"0","chance_cnt":"1010"},"scoreM":{"rank":"3","reg_dates":"12.24","score":"1010","pno":null,"uname":"\uc6d0\uc885\ud0dc"},"list_salt":{"list_salt_get":[{"reg_date":"2022-12-24 23:13:54","chance_type":"add","chance_type2":"snsshare","current":"1000"},{"reg_date":"2022-12-24 23:06:15","chance_type":"login","chance_type2":"","current":"10"}],"list_salt_use":[]},"play_list":{"game_list":[{"chance_type2":"snsshare","cnt":"1"}],"use_list":[]},"chking":null,"end":1140}