{"mode":"CHARGE_CHANCE","result":"o","chance_info":{"emtpy":"0","ssn":"YdSYDDQedCReyU9","reg_date":"2023-04-15 20:46:57","uname":"A*2","pno":"01024953583","profile_image":"\/images\/profile_default.jpg","member_type":"3","total_chance":"74166","use_chance":"-69200","login_today":"300","gift_today":"0","sns_today":"0","add_today":"0","use_today":"0","chance_today_cnt":"300","chance_cnt":"4966","uname_origin":"AT2","pno_origin":"01024953583","birthday_origin":"19780905","usex_origin":"\ub0a8"},"scoreM":{"jjansun_week":{"gamecode":"jjansun_week","rank":"1012","reg_dates":"06.10","score":"100","pno":"3583","uname":"AT2"},"jjansun_accumulate":{"gamecode":"jjansun_accumulate","rank":"13","reg_dates":"06.10","score":"61066","pno":"3583","uname":"AT2"}},"list_salt":{"list_salt_2x":[{"gamecode":"game12","gamename":"\uc0ac\uc790\uc131\uc5b4","codename":"saltboom","val":"2"}],"joincnt_game13":{"0":"1058","join_cnt":"1058"},"list_levelup":[{"reg_date":"2023-05-13 06:06:54","action_type_str":"\ub204\uc801 50,000\uc774\uc0c1"},{"reg_date":"2023-04-16 17:42:02","action_type_str":"\uac1c\uc778\uc815\ubcf4 \uc5c5\ub370\uc774\ud2b8"}],"list_salt_get":[{"reg_date":"2023-06-10 10:16:56","current":"300","chance_type":"add","chance_type2":"\ub85c\uadf8\uc778"},{"reg_date":"2023-06-09 21:24:35","current":"300","chance_type":"add","chance_type2":"\ub85c\uadf8\uc778"},{"reg_date":"2023-06-08 21:41:29","current":"300","chance_type":"add","chance_type2":"\ub85c\uadf8\uc778"},{"reg_date":"2023-06-07 00:33:30","current":"300","chance_type":"add","chance_type2":"\ub85c\uadf8\uc778"},{"reg_date":"2023-06-05 00:29:26","current":"100","chance_type":"add","chance_type2":"\uc801\ub9bd\uac8c\uc784"}],"list_salt_use":[{"reg_date":"2023-05-18 22:41:17","chance_type":"use","chance_type2":"use4","gamename":"\uce74\ub4dc\ubf51\uae30","current":"-100","win_type_str":"Npay1000"},{"reg_date":"2023-05-12 00:30:03","chance_type":"use","chance_type2":"use1","gamename":"\uc989\uc11d\ubcf5\uad8c","current":"-100","win_type_str":"\ubc14\ub098\ub098\uc6b0\uc720"},{"reg_date":"2023-04-28 00:33:20","chance_type":"use","chance_type2":"use2","gamename":"\ub8f0\ub81b","current":"-100","win_type_str":"\uc2a4\ud0c0\ubc85\uc2a4\ucee4\ud53c"},{"reg_date":"2023-04-22 00:43:20","chance_type":"use","chance_type2":"use1","gamename":"\uc989\uc11d\ubcf5\uad8c","current":"-100","win_type_str":"Npay1000"},{"reg_date":"2023-04-18 00:22:35","chance_type":"use","chance_type2":"use2","gamename":"\ub8f0\ub81b","current":"-100","win_type_str":"Npay1000"}]},"play_list":{"game_list":[],"use_list":[]},"chking":null,"end":112}